utterughs/__init__.py
utterughs/ughs.py
UtterUghs-0.1.dist-info/LICENSE.md
UtterUghs-0.1.dist-info/METADATA
UtterUghs-0.1.dist-info/WHEEL
UtterUghs-0.1.dist-info/top_level.txt
UtterUghs-0.1.dist-info/RECORD
