Metadata-Version: 2.1
Name: UtterUghs
Version: 0.1
Summary: Do you want a package to spit out utter ughs for you? Here you go!
Author: Nyi Nyi Nyan Lin
Author-email: nyinyinyanlin.mm@gmail.com
License: WTFPL
License-File: LICENSE.md
